drf_dynamics/__init__.py
drf_dynamics/helpers.py
drf_dynamics/mixins.py
drf_dynamics/specs.py
drf_dynamics-0.0.4.dist-info/LICENCE
drf_dynamics-0.0.4.dist-info/METADATA
drf_dynamics-0.0.4.dist-info/WHEEL
drf_dynamics-0.0.4.dist-info/top_level.txt
drf_dynamics-0.0.4.dist-info/RECORD
